cfchecker/__init__.py
cfchecker/cfchecks.py
cfchecker-4.1.0.dist-info/LICENSE
cfchecker-4.1.0.dist-info/METADATA
cfchecker-4.1.0.dist-info/WHEEL
cfchecker-4.1.0.dist-info/entry_points.txt
cfchecker-4.1.0.dist-info/top_level.txt
cfchecker-4.1.0.dist-info/RECORD
