Metadata-Version: 2.1
Name: cfchecker
Version: 4.1.0
Summary: The NetCDF Climate Forecast Conventions compliance checker
Home-page: http://cfconventions.org/compliance-checker.html
Author: Rosalyn Hatcher
Author-email: r.s.hatcher@reading.ac.uk
License: UNKNOWN
Platform: UNKNOWN
Classifier: Development Status :: 5 - Production/Stable
Classifier: Topic :: Software Development :: Libraries
Classifier: Topic :: Scientific/Engineering :: Atmospheric Science
Classifier: Intended Audience :: Science/Research
Classifier: Natural Language :: English
Classifier: License :: OSI Approved :: BSD License
Classifier: Operating System :: MacOS
Classifier: Operating System :: POSIX :: Linux
Classifier: Programming Language :: Python :: 3
Classifier: Programming Language :: Python :: 3.6
Classifier: Programming Language :: Python :: 3.7
Classifier: Programming Language :: Python :: 3.8
Classifier: Programming Language :: Python :: 3.9
Requires-Python: >3
Requires-Dist: netCDF4
Requires-Dist: numpy (>=1.7)
Requires-Dist: cfunits (>=3.0.0)
Requires-Dist: future
